Workbook

Sheet - AYUDA -
B4: Ayuda

Sheet Componenetes de Hardware
B5: Comparación de Precios entre diferentes proveedores
J7: ESTADÍSTICAS POR PRODUCTO
B8: PRODUCTO | C8: CANTIDAD | D8: Mercado libre | E8: Amazon | F8: Katronix | G8: PROVEEDOR 4 | H8: PROVEEDOR 5 | I8: PROVEEDOR 6 | J8: PRECIO MÁS BAJO | K8: PRECIO PROMEDIO | L8: PRECIO MÁS ALTO
B9: Cpu Torre Core I5 +16ram+hd500 Monitor 19 | C9: 4 | D9: 750000 | E9: 1322000 | F9: 2399070 | J9: =MIN('Componenetes de Hardware'!$D9:$I9) -> 750000 | K9: =IFERROR(AVERAGE('Componenetes de Hardware'!$D9:$I9),0) -> 1490356.7 | L9: =MAX('Componenetes de Hardware'!$D9:$I9) -> 2399070
B10: Monitor Curvo 27 Fhd Diseño Sin Bordes Color Black 100V/240V | C10: 4 | D10: 650000 | E10: 616000 | F10: 1300000 | J10: =MIN('Componenetes de Hardware'!$D10:$I10) -> 616000 | K10: =IFERROR(AVERAGE('Componenetes de Hardware'!$D10:$I10),0) -> 855333.33 | L10: =MAX('Componenetes de Hardware'!$D10:$I10) -> 1300000
B11: Disco sólido SSD interno Crucial CT500BX500SSD1 500GB negro | C11: 4 | D11: 190000 | E11: 597000 | F11: 500000 | J11: =MIN('Componenetes de Hardware'!$D11:$I11) -> 190000 | K11: =IFERROR(AVERAGE('Componenetes de Hardware'!$D11:$I11),0) -> 429000 | L11: =MAX('Componenetes de Hardware'!$D11:$I11) -> 597000
B12: Disco sólido SSD interno Kingston SA400S37/240GB Negro | C12: 4 | D12: 165900 | E12: 251000 | F12: 500000 | J12: =MIN('Componenetes de Hardware'!$D12:$I12) -> 165900 | K12: =IFERROR(AVERAGE('Componenetes de Hardware'!$D12:$I12),0) -> 305633.33 | L12: =MAX('Componenetes de Hardware'!$D12:$I12) -> 500000
B13: Poweredge T150 - Tower Server/ Intel Xeon E-2336g/16gb/2tb | C13: 1 | D13: 6174900 | E13: 4870800 | F13: 0 | J13: =MIN('Componenetes de Hardware'!$D13:$I13) -> 0 | K13: =IFERROR(AVERAGE('Componenetes de Hardware'!$D13:$I13),0) -> 3681900 | L13: =MAX('Componenetes de Hardware'!$D13:$I13) -> 6174900
B14: MEMORIA RAM DDR4 16G 3200 CORSAIR VENGEANCE RGB RS | C14: 4 | D14: 390000 | E14: 559000 | F14: 0 | J14: =MIN('Componenetes de Hardware'!$D14:$I14) -> 0 | K14: =IFERROR(AVERAGE('Componenetes de Hardware'!$D14:$I14),0) -> 316333.33 | L14: =MAX('Componenetes de Hardware'!$D14:$I14) -> 559000
B15: Combo Dell Wireless Km3322w Teclado + Mouse | C15: 4 | D15: 125900 | E15: 123000 | F15: 119000 | J15: =MIN('Componenetes de Hardware'!$D15:$I15) -> 119000 | K15: =IFERROR(AVERAGE('Componenetes de Hardware'!$D15:$I15),0) -> 122633.33 | L15: =MAX('Componenetes de Hardware'!$D15:$I15) -> 125900
B16: Mouse gamer vertical inalámbrico recargable Weibo WB-881 negro | C16: 4 | D16: 109000 | E16: 90000 | F16: 79000 | J16: =MIN('Componenetes de Hardware'!$D16:$I16) -> 79000 | K16: =IFERROR(AVERAGE('Componenetes de Hardware'!$D16:$I16),0) -> 92666.667 | L16: =MAX('Componenetes de Hardware'!$D16:$I16) -> 109000
B17: Licencia Windows 11 Pro ESD Vitalicia | C17: 4 | D17: 60000 | E17: 371000 | F17: 1090000 | J17: =MIN('Componenetes de Hardware'!$D17:$I17) -> 60000 | K17: =IFERROR(AVERAGE('Componenetes de Hardware'!$D17:$I17),0) -> 507000 | L17: =MAX('Componenetes de Hardware'!$D17:$I17) -> 1090000
B18: Total | D18: =ROUND(SUMPRODUCT('Componenetes de Hardware'!$C$9:$C$17,'Componenetes de Hardware'!$D$9:$D$17),2) -> 15938100 | E18: =ROUND(SUMPRODUCT('Componenetes de Hardware'!$C$9:$C$17,'Componenetes de Hardware'!$E$9:$E$17),2) -> 20586800 | F18: =ROUND(SUMPRODUCT('Componenetes de Hardware'!$C$9:$C$17,'Componenetes de Hardware'!$F$9:$F$17),2) -> 23948280 | G18: =ROUND(SUMPRODUCT('Componenetes de Hardware'!$C$9:$C$17,'Componenetes de Hardware'!$G$9:$G$17),2) -> 0 | H18: =ROUND(SUMPRODUCT('Componenetes de Hardware'!$C$9:$C$17,'Componenetes de Hardware'!$H$9:$H$17),2) -> 0 | I18: =ROUND(SUMPRODUCT('Componenetes de Hardware'!$C$9:$C$17,'Componenetes de Hardware'!$I$9:$I$17),2) -> 0
B21: DATOS ADICIONALES
B22: TIEMPO DE ENTREGA (DÍAS) | D22: 1 a 2 dias habiles | E22: 5 a 10 dias habiles | F22: 1 a 8 dias habiles
B23: COSTO DE ENVÍO | D23: 70000 | E23: 34000 | F23: 0 | G23: 0 | H23: 0 | I23: 0
B24: FORMAS DE PAGO
D26: contado | E26: contado | F26: contado | G26: N/A | H26: N/A | I26: N/A
D27: Targeta de credito | E27: Targeta de credito | F27: Targeta de credito
B29: Total | D29: =SUM('Componenetes de Hardware'!$D$18+D23) -> 16008100 | E29: =SUM('Componenetes de Hardware'!$E$18+E23) -> 20620800 | F29: =SUM('Componenetes de Hardware'!$F$18+F23) -> 23948280

Sheet Software
B5: Software
J7: ESTADÍSTICAS POR PRODUCTO | M7: Total
B8: CATEGORIA | C8: CANTIDAD | D8: Visual Studio code | E8: Visual Studio pro(anual) | F8: IntelliJ IDEA | G8: IntelliJ IDEA Ultimate(anual) | H8: Android Studio | I8: Xcode | J8: PRECIO MÁS BAJO | K8: PRECIO PROMEDIO | L8: PRECIO MÁS ALTO | M8: . | N8: Columna2
B9: IDEs y Entornos de Desarrollo | C9: 4 | D9: 0 | E9: 2500000 | F9: 0 | G9: 3300000 | H9: 0 | I9: 0 | J9: =MIN(Software!$D9:$I9) -> 0 | K9: =IFERROR(AVERAGE(Software!$D9:$I9),0) -> 966666.67 | L9: =MAX(Software!$D9:$I9) -> 3300000 | M9: =SUM(Software!$D9:$I9) -> 5800000 | N9: =MAX(Software!$D9:$I9) -> 3300000
B10: CATEGORIA | C10: CANTIDAD | D10: Ionic | E10: Ionic Plan Pro | F10: Xamarin | G10: Flutter | H10: React Native | I10: React.js | J10: PRECIO MÁS BAJO | K10: PRECIO PROMEDIO | L10: PRECIO MÁS ALTO
B11: Frameworks para Aplicaciones Móviles | C11: 4 | D11: 0 | E11: 1800000 | F11: 0 | G11: 0 | H11: 0 | I11: 0 | J11: =MIN(Software!$D11:$I11) -> 0 | K11: =IFERROR(AVERAGE(Software!$D11:$I11),0) -> 300000 | L11: =MAX(Software!$D11:$I11) -> 1800000 | M11: =SUM(D11:I11) -> 1800000
B12: CATEGORIA | C12: CANTIDAD | D12: Alojamiento Servidor | E12: Node.js+Express | F12: Django | G12: Laravel | H12: Spring Boot | I12: Npm/Yarn | J12: PRECIO MÁS BAJO | K12: PRECIO PROMEDIO | L12: PRECIO MÁS ALTO
B13: Backend y Servidores | C13: 1 | D13: 3000000 | E13: 0 | F13: 0 | G13: 0 | H13: 0 | I13: 0 | J13: =MIN(Software!$D13:$I13) -> 0 | K13: =IFERROR(AVERAGE(Software!$D13:$I13),0) -> 500000 | L13: =MAX(Software!$D13:$I13) -> 3000000 | M13: =SUM(D13:I13) -> 3000000
B14: CATEGORIA | C14: CANTIDAD | D14: MongoDB | E14: MongoDB Atlas M10(anual) | F14: Supabase | G14: Supabase Pro | H14: MySQL | I14: Workbench | J14: PRECIO MÁS BAJO | K14: PRECIO PROMEDIO | L14: PRECIO MÁS ALTO
B15: Bases de Datos | C15: 1 | D15: 0 | E15: 5000000 | F15: 0 | G15: 1350000 | H15: 0 | I15: 0 | J15: =MIN(Software!$D15:$I15) -> 0 | K15: =IFERROR(AVERAGE(Software!$D15:$I15),0) -> 1058333.3 | L15: =MAX(Software!$D15:$I15) -> 5000000 | M15: =SUM(D15:I15) -> 6350000
B16: CATEGORIA | C16: CANTIDAD | D16: Figma | E16: Figma Professional (anual) | F16: Sketch(anual) | G16: Canva | H16: Canva Pro (anual) | J16: PRECIO MÁS BAJO | K16: PRECIO PROMEDIO | L16: PRECIO MÁS ALTO
B17: Herramientas de Diseño y Prototipado | C17: 4 | D17: 0 | E17: 670000 | F17: 550000 | G17: 0 | H17: 500000 | J17: =MIN(Software!$D17:$I17) -> 0 | K17: =IFERROR(AVERAGE(Software!$D17:$I17),0) -> 344000 | L17: =MAX(Software!$D17:$I17) -> 670000 | M17: =SUM(D17:I17) -> 1720000
B18: CATEGORIA | C18: CANTIDAD | D18: Git Hub+ Git | E18: Git Hub Pro (anual) | F18: Bitbucket | G18: Bitbucket Standart plan (anual) | H18: Git Lab | I18: Git Lab premium (anual | J18: PRECIO MÁS BAJO | K18: PRECIO PROMEDIO | L18: PRECIO MÁS ALTO
B19: Control de Versiones | C19: 4 | D19: 0 | E19: 460000 | F19: 0 | G19: 160000 | H19: 0 | I19: 1400000 | J19: =MIN(Software!$D19:$I19) -> 0 | K19: =IFERROR(AVERAGE(Software!$D19:$I19),0) -> 336666.67 | L19: =MAX(Software!$D19:$I19) -> 1400000 | M19: =SUM(D19:I19) -> 2020000
B20: CATEGORIA | C20: CANTIDAD | D20: Postman | E20: Postman Professional | F20: Swagger | G20: Jest | H20: Junit | I20: Selenium | J20: PRECIO MÁS BAJO | K20: PRECIO PROMEDIO | L20: PRECIO MÁS ALTO
B21: Pruebas y Depuración | C21: 4 | D21: 0 | E21: 500000 | F21: 0 | G21: 0 | H21: 0 | I21: 0 | J21: =MIN(Software!$D21:$I21) -> 0 | K21: =IFERROR(AVERAGE(Software!$D21:$I21),0) -> 83333.333 | L21: =MAX(Software!$D21:$I21) -> 500000 | M21: =SUM(D21:I21) -> 500000
B22: CATEGORIA | C22: CANTIDAD | D22: Trello | E22: Trello premium | F22: Google Workspace Business Standard | G22: Google Workspace Business Standard | H22: Notio | I22: Notio Business | J22: PRECIO MÁS BAJO | K22: PRECIO PROMEDIO | L22: PRECIO MÁS ALTO
B23: Herramientas de Productividad y Colaboración | C23: 4 | D23: 0 | E23: 460000 | F23: 0 | G23: 632000 | H23: 0 | I23: 902000 | J23: =MIN(Software!$D23:$I23) -> 0 | K23: =IFERROR(AVERAGE(Software!$D23:$I23),0) -> 332333.33 | L23: =MAX(Software!$D23:$I23) -> 902000 | M23: =SUM(D23:I23) -> 1994000
B24: CATEGORIA | C24: CANTIDAD | D24: Google Cloud | E24: Hostinger | F24: DigitalOcean | G24: AWS | H24: Hetzner | J24: PRECIO MÁS BAJO | K24: PRECIO PROMEDIO | L24: PRECIO MÁS ALTO
B25: HOSTING | C25: 1 | D25: 1740000 | E25: 780000 | F25: 1084800 | G25: 1800000 | H25: 600000 | I25: 902000 | J25: =MIN(Software!$D25:$I25) -> 600000 | K25: =IFERROR(AVERAGE(Software!$D25:$I25),0) -> 1151133.3 | L25: =MAX(Software!$D25:$I25) -> 1800000 | M25: =SUM(D25:I25) -> 6906800
B27: lENGUAJES | C27: CANTIDAD
B28: JavaScript | C28: 1
B29: HTML5 + CSS3 | C29: 1
B30: My SQL | C30: 1

Sheet Mano de obra
B5: Mano de obra
J7: ESTADÍSTICAS POR PRODUCTO
B8: CONCEPTO | C8: Cantidad | D8: Salario(Mensual Uni) | E8: Salario(Anual Uni) | F8: Salario(Anual General)
B9: Full Stack Junior | C9: 4 | D9: 4000000 | E9: ='Mano de obra'!$D9*12 -> 48000000 | F9: ='Mano de obra'!$D9*'Mano de obra'!$C9*12 -> 192000000

Sheet Total
B6: Concepto | C6: Costo
B7: Hardware | C7: 16008100
B8: Software | C8: 2308800
B9: Mano de obra | C9: 192000000
B10: Contingencia | C10: 900000
B11: Total Final | C11: =SUM(C7:C10) -> 211216900

Sheet Soporte
B7: Almendras | C7: 1 | D7: 498 | E7: 420 | F7: 450 | G7: 230 | H7: 600 | I7: 520
B8: Nueces | C8: 2 | D8: 450 | E8: 220 | F8: 405 | G8: 495 | H8: 540 | I8: 200
B9: Pistachos | C9: 2 | D9: 650 | E9: 620 | F9: 666 | G9: 400 | H9: 648 | I9: 452.4
B10: Pecán | C10: 1 | D10: 585 | E10: 558 | F10: 320 | G10: 360 | H10: 583.2 | I10: 407.16
B11: Bananas | C11: 3 | D11: 526.5 | E11: 502.2 | F11: 539.46 | G11: 300 | H11: 500 | I11: 366.44
B12: Pasas | C12: 1 | D12: 473.8 | E12: 200 | F12: 485.51 | G12: 291.6 | H12: 270 | I12: 220
D19: 30 | E19: 10 | F19: 15 | G19: 15 | H19: 15 | I19: 10
D20: 10 | E20: 10 | F20: 10 | G20: Gratis | H20: 5 | I20: Gratis
D21: Efvo | E21: Efvo | F21: Mercado Pago | G21: Efectivo | H21: Mercado Pago | I21: Mercado Pago
D22: Tarjeta | E22: Tarjeta | F22: Tarjeta cuotas | G22: Mercado Pago | H22: Tarjeta cuotas | I22: Tarjeta cuotas
B28: Piñones | C28: 1 | D28: 340 | E28: 330 | F28: 440 | G28: 400 | H28: 320 | I28: 330
B29: Cranberries | C29: 1 | D29: 220 | E29: 230 | F29: 240 | G29: 220 | H29: 219 | I29: 218
B30: Castañas | C30: 2 | D30: 560 | E30: 580 | F30: 550 | G30: 520 | H30: 551 | I30: 550
B35: China Co
B36: 250
B37: 440
B38: 440
B39: 350
B40: 420
B41: 199
